dhc30/__init__.py
dhc30/dhc30.py
dhc30-0.0.1.dist-info/METADATA
dhc30-0.0.1.dist-info/WHEEL
dhc30-0.0.1.dist-info/top_level.txt
dhc30-0.0.1.dist-info/RECORD
