Metadata-Version: 2.1
Name: dhc30
Version: 0.0.1
Summary: UNKNOWN
Home-page: UNKNOWN
Author: Duver Hernandez Cobos
License: UNKNOWN
Platform: UNKNOWN
Requires-Dist: numpy
